mcp_sentry/__init__.py
mcp_sentry/__main__.py
mcp_sentry/server.py
mcp_sentry_fastmcp-0.6.3.dist-info/METADATA
mcp_sentry_fastmcp-0.6.3.dist-info/WHEEL
mcp_sentry_fastmcp-0.6.3.dist-info/entry_points.txt
mcp_sentry_fastmcp-0.6.3.dist-info/RECORD
