Metadata-Version: 2.4
Name: mcp-sentry-fastmcp
Version: 0.6.3
Summary: MCP server for retrieving issues from sentry.io
Project-URL: Homepage, https://github.com/fastmcp-me/mcp-sentry#readme
Project-URL: Repository, https://github.com/fastmcp-me/mcp-sentry.git
Project-URL: Issues, https://github.com/fastmcp-me/mcp-sentry/issues
Requires-Python: >=3.10
Requires-Dist: mcp>=1.0.0
